Workbook
Name AvgImplied: Valuation!$C$15
Name BeatThresh: Inputs!$D$38
Name Beta: Inputs!$D$31
Name ConsEBITDA: Consensus!$D$5
Name ConsEPS: Consensus!$D$7
Name ConsNI: Consensus!$D$6
Name ConsRev: Consensus!$D$4
Name CostDebt: Inputs!$D$32
Name ERP: Inputs!$D$30
Name EV: Valuation!$C$4
Name EbitdaMarginMy: Inputs!$D$16
Name EbitdaMy: MyModel!$C$5
Name EpsMy: MyModel!$C$7
Name FairValue: Valuation!$C$34
Name FcfBase: MyModel!$C$8
Name FcfConv: Inputs!$D$18
Name GrowthFade: Inputs!$D$15
Name KpiNames: SectorKPIs!$C$4:$I$8
Name KpiValues: SectorKPIs!$C$11:$I$15
Name MissThresh: Inputs!$D$39
Name NetDebt: Inputs!$D$8
Name NiMarginMy: Inputs!$D$17
Name NiMy: MyModel!$C$6
Name PeerEVEBITDA: Inputs!$D$23
Name PeerEVRev: Inputs!$D$25
Name PeerPE: Inputs!$D$24
Name PeerPS: Inputs!$D$26
Name Price: Inputs!$D$6
Name PriorEBITDA: Consensus!$C$5
Name PriorNI: Consensus!$C$6
Name PriorRev: Consensus!$C$4
Name ReactSens: Inputs!$D$40
Name RevGrowthMy: Inputs!$D$14
Name RevMy: MyModel!$C$4
Name RiskFree: Inputs!$D$29
Name ScenarioMult: Inputs!$D$20
Name ScenarioName: Inputs!$D$19
Name SectorList: SectorKPIs!$C$3:$I$3
Name SelectedSector: Dashboard!$G$3
Name Shares: Inputs!$D$7
Name TaxRate: Inputs!$D$9
Name TermGrowth: Inputs!$D$35
Name Ticker: Inputs!$D$5
Name WACC: Valuation!$C$20
Name WeightDebt: Inputs!$D$34
Name WeightEquity: Inputs!$D$33

Sheet Dashboard
A1: SECTOR CONSENSUS vs MY MODEL — EQUITY DASHBOARD
A3: Company | B3: =Inputs!D4 -> Nimbus Cloud Inc | E3: Sector | G3: Tech/SaaS | I3: Current Price | J3: =Price -> 45
A4: Ticker | B4: =Inputs!D5 -> NIMB | E4: Next Earnings | F4: =Inputs!D10 -> 46231 | I4: Shares (M) | J4: =Shares -> 100
B6: REVENUE ($M) | F6: EBITDA ($M) | J6: NET INCOME ($M)
B7: My | C7: =RevMy -> 1160 | F7: My | G7: =EbitdaMy -> 301.6 | J7: My | K7: =NiMy -> 156.6
B8: Consensus | C8: =ConsRev -> 1150 | F8: Consensus | G8: =ConsEBITDA -> 295 | J8: Consensus | K8: =ConsNI -> 150
B9: YoY | C9: =RevMy/PriorRev-1 -> 0.16 | F9: YoY | G9: =EbitdaMy/PriorEBITDA-1 -> 0.2064 | J9: YoY | K9: =NiMy/PriorNI-1 -> 0.305
B10: vs Cons | C10: =RevMy/ConsRev-1 -> 0.0086956522 | F10: vs Cons | G10: =EbitdaMy/ConsEBITDA-1 -> 0.022372881 | J10: vs Cons | K10: =NiMy/ConsNI-1 -> 0.044
B11: Signal | C11: =IF(RevMy/ConsRev-1>=BeatThresh,"BEAT",IF(RevMy/ConsRev-1<=MissThresh,"MISS","IN-LINE")) -> IN-LINE | F11: Signal | G11: =IF(EbitdaMy/ConsEBITDA-1>=BeatThresh,"BEAT",IF(EbitdaMy/ConsEBITDA-1<=MissThresh,"MISS","IN-LINE")) -> BEAT | J11: Signal | K11: =IF(NiMy/ConsNI-1>=BeatThresh,"BEAT",IF(NiMy/ConsNI-1<=MissThresh,"MISS","IN-LINE")) -> BEAT
B13: SECTOR KPI SUMMARY (auto-updates with sector)
B14: =INDEX(KpiNames,1,MATCH(SelectedSector,SectorList,0)) -> ARR ($M) | D14: =INDEX(KpiNames,2,MATCH(SelectedSector,SectorList,0)) -> Net Rev Retention (%) | F14: =INDEX(KpiNames,3,MATCH(SelectedSector,SectorList,0)) -> Rule of 40 (%) | H14: =INDEX(KpiNames,4,MATCH(SelectedSector,SectorList,0)) -> Gross Margin (%) | J14: =INDEX(KpiNames,5,MATCH(SelectedSector,SectorList,0)) -> CAC Payback (mo)
B15: =INDEX(KpiValues,1,MATCH(SelectedSector,SectorList,0)) -> 1200 | D15: =INDEX(KpiValues,2,MATCH(SelectedSector,SectorList,0)) -> 118 | F15: =INDEX(KpiValues,3,MATCH(SelectedSector,SectorList,0)) -> 46 | H15: =INDEX(KpiValues,4,MATCH(SelectedSector,SectorList,0)) -> 78 | J15: =INDEX(KpiValues,5,MATCH(SelectedSector,SectorList,0)) -> 14
B17: VALUATION
B18: EV/EBITDA | C18: P/E | D18: EV/Rev | E18: P/S | F18: DCF Fair Value | G18: Avg Implied | H18: Current Price | I18: DCF Upside
B19: =Valuation!C5 -> 14.423077 | C19: =Valuation!C6 -> 28.735632 | D19: =Valuation!C7 -> 3.75 | E19: =Valuation!C8 -> 3.8793103 | F19: =FairValue -> 45.857753 | G19: =AvgImplied -> 48.165 | H19: =Price -> 45 | I19: =Valuation!C35 -> 0.019061179
B21: EARNINGS SIGNAL — Beat/Miss & implied stock move
B22: Blended Surprise | D22: =AVERAGE(RevMy/ConsRev-1,EbitdaMy/ConsEBITDA-1,NiMy/ConsNI-1) -> 0.025022845 | F22: Signal | H22: =IF(D22>=BeatThresh,"LIKELY BEAT ▲",IF(D22<=MissThresh,"LIKELY MISS ▼","IN-LINE ►")) -> LIKELY BEAT ▲
B23: Implied Stock Move | D23: =D22*ReactSens -> 0.20018276 | F23: Rule | H23: =("Beat>"&TEXT(BeatThresh,"0.0%")&" / Miss<"&TEXT(MissThresh,"0.0%")) -> Beat>2.0% / Miss<-2.0%
B40: Tip: change the Sector dropdown (orange cell, G3) or any Inputs value — the entire model recomputes.
B43: Metric | C43: Consensus | D43: My Model
B44: Revenue | C44: =ConsRev -> 1150 | D44: =RevMy -> 1160
B45: EBITDA | C45: =ConsEBITDA -> 295 | D45: =EbitdaMy -> 301.6
B46: Net Income | C46: =ConsNI -> 150 | D46: =NiMy -> 156.6

Sheet Inputs
A1: INPUTS — edit anything; the model recomputes live
B3: GENERAL | F3: LOAD EXAMPLE TEMPLATE
B4: Company | D4: Nimbus Cloud Inc | F4: Copy a row into General to switch sample company:
B5: Ticker | D5: NIMB
B6: Current Price ($) | D6: 45 | F6: Company | G6: Ticker | H6: Sector | I6: Price | J6: Shares | K6: NetDebt
B7: Shares Outstanding (M) | D7: 100 | F7: Nimbus Cloud Inc | G7: NIMB | H7: Tech/SaaS | I7: 45 | J7: 100 | K7: -150
B8: Net Debt ($M) [negative = net cash] | D8: -150 | F8: MetroMart Retail | G8: MMRT | H8: Consumer/Retail | I8: 62 | J8: 210 | K8: 480
B9: Tax Rate | D9: 0.21 | F9: Helios Energy | G9: HELI | H9: Energy | I9: 95 | J9: 400 | K9: 6000
B10: Next Earnings Date | D10: 46231
B11: Selected Sector (from Dashboard) | D11: =SelectedSector -> Tech/SaaS
B13: MY ASSUMPTIONS
B14: Revenue Growth (Year 1) | D14: 0.16
B15: Growth Fade (per year) | D15: 0.03
B16: EBITDA Margin | D16: 0.26
B17: Net Margin | D17: 0.135
B18: FCF Conversion | D18: 0.85
B19: Scenario | D19: Base
B20: Scenario Growth Multiplier | D20: =IF(ScenarioName="Bull",1.25,IF(ScenarioName="Bear",0.7,1)) -> 1
B22: CONSENSUS / PEER MULTIPLES
B23: Peer EV/EBITDA | D23: 13
B24: Peer P/E | D24: 22
B25: Peer EV/Revenue | D25: 5
B26: Peer P/S | D26: 5
B28: DCF / WACC
B29: Risk-free Rate | D29: 0.042
B30: Equity Risk Premium | D30: 0.05
B31: Beta | D31: 1.2
B32: Pre-tax Cost of Debt | D32: 0.06
B33: Weight — Equity | D33: 0.85
B34: Weight — Debt | D34: 0.15
B35: Terminal Growth | D35: 0.03
B37: BEAT / MISS RULES (editable)
B38: Beat Threshold (surprise %) | D38: 0.02
B39: Miss Threshold (surprise %) | D39: -0.02
B40: Reaction Sensitivity (move per 1% surprise) | D40: 8
B42: REAL-TIME DATA (placeholders — wire to a feed)
B43: Live Price
B44: Live Consensus Revenue ($M)
B45: Live Consensus EPS
B46: Last Updated

Sheet Consensus
A1: MARKET CONSENSUS
B3: Metric ($M) | C3: Prior FY (Actual) | D3: Current FY (Consensus) | E3: NTM (Consensus)
B4: Revenue | C4: 1000 | D4: 1150 | E4: 1300
B5: EBITDA | C5: 250 | D5: 295 | E5: 340
B6: Net Income | C6: 120 | D6: 150 | E6: 175
B7: EPS ($) | C7: =C6/Shares -> 1.2 | D7: =D6/Shares -> 1.5 | E7: =E6/Shares -> 1.75

Sheet MyModel
A1: MY MODEL — projections from assumptions
B3: Metric ($M) | C3: My Projection | D3: Formula / Driver
B4: Revenue | C4: =PriorRev*(1+RevGrowthMy*ScenarioMult) -> 1160 | D4: Prior Rev × (1 + growth × scenario)
B5: EBITDA | C5: =RevMy*EbitdaMarginMy -> 301.6 | D5: Revenue × EBITDA margin
B6: Net Income | C6: =RevMy*NiMarginMy -> 156.6 | D6: Revenue × net margin
B7: EPS ($) | C7: =NiMy/Shares -> 1.566 | D7: Net income ÷ shares
B8: FCF (Year 0, $M) | C8: =EbitdaMy*(1-TaxRate)*FcfConv -> 202.5244 | D8: EBITDA × (1-tax) × FCF conversion

Sheet Valuation
A1: VALUATION — multiples, DCF & sensitivity
B3: MARKET MULTIPLES (My Model)
B4: Enterprise Value ($M) | C4: =Price*Shares+NetDebt -> 4350
B5: EV / EBITDA | C5: =EV/EbitdaMy -> 14.423077
B6: P / E | C6: =Price/EpsMy -> 28.735632
B7: EV / Revenue | C7: =EV/RevMy -> 3.75
B8: P / S | C8: =Price*Shares/RevMy -> 3.8793103
B10: IMPLIED PRICE (Peer Multiples)
B11: via EV/EBITDA | C11: =(PeerEVEBITDA*EbitdaMy-NetDebt)/Shares -> 40.708
B12: via P/E | C12: =PeerPE*EpsMy -> 34.452
B13: via EV/Revenue | C13: =(PeerEVRev*RevMy-NetDebt)/Shares -> 59.5
B14: via P/S | C14: =PeerPS*RevMy/Shares -> 58
B15: Average Implied Price | C15: =AVERAGE(C11:C14) -> 48.165
B17: WACC
B18: Cost of Equity | C18: =RiskFree+Beta*ERP -> 0.102
B19: After-tax Cost of Debt | C19: =CostDebt*(1-TaxRate) -> 0.0474
B20: WACC | C20: =WeightEquity*C18+WeightDebt*C19 -> 0.09381
B22: DCF — 5-YEAR PROJECTION
B23: Year | C23: 1 | D23: 2 | E23: 3 | F23: 4 | G23: 5
B24: Rev Growth | C24: =MAX(RevGrowthMy*ScenarioMult,TermGrowth) -> 0.16 | D24: =MAX(C24-GrowthFade,TermGrowth) -> 0.13 | E24: =MAX(D24-GrowthFade,TermGrowth) -> 0.1 | F24: =MAX(E24-GrowthFade,TermGrowth) -> 0.07 | G24: =MAX(F24-GrowthFade,TermGrowth) -> 0.04
B25: Revenue ($M) | C25: =RevMy*(1+C24) -> 1345.6 | D25: =C25*(1+D24) -> 1520.528 | E25: =D25*(1+E24) -> 1672.5808 | F25: =E25*(1+F24) -> 1789.6615 | G25: =F25*(1+G24) -> 1861.2479
B26: EBITDA ($M) | C26: =C25*EbitdaMarginMy -> 349.856 | D26: =D25*EbitdaMarginMy -> 395.33728 | E26: =E25*EbitdaMarginMy -> 434.87101 | F26: =F25*EbitdaMarginMy -> 465.31198 | G26: =G25*EbitdaMarginMy -> 483.92446
B27: FCF ($M) | C27: =C26*(1-TaxRate)*FcfConv -> 234.9283 | D27: =D26*(1-TaxRate)*FcfConv -> 265.46898 | E27: =E26*(1-TaxRate)*FcfConv -> 292.01588 | F27: =F26*(1-TaxRate)*FcfConv -> 312.45699 | G27: =G26*(1-TaxRate)*FcfConv -> 324.95527
B29: PV of explicit FCF | C29: =NPV(WACC,C27:G27) -> 1085.6379
B30: Terminal Value | C30: =G27*(1+TermGrowth)/(WACC-TermGrowth) -> 5245.321
B31: PV of Terminal Value | C31: =C30/(1+WACC)^5 -> 3350.1374
B32: Enterprise Value (DCF) | C32: =C29+C31 -> 4435.7753
B33: Equity Value (DCF) | C33: =C32-NetDebt -> 4585.7753
B34: Fair Value / Share | C34: =C33/Shares -> 45.857753
B35: Upside vs Price | C35: =FairValue/Price-1 -> 0.019061179
B37: SENSITIVITY — Fair Value / Share (WACC × Terminal Growth)
B38: WACC ↓ / g → | C38: =TermGrowth+-0.01 -> 0.02 | D38: =TermGrowth+-0.005 -> 0.025 | E38: =TermGrowth+0 -> 0.03 | F38: =TermGrowth+0.005 -> 0.035 | G38: =TermGrowth+0.01 -> 0.04
B39: =WACC+-0.01 -> 0.08381 | C39: =(NPV($B39,$C$27:$G$27)+($G$27*(1+C$38)/($B39-C$38))/(1+$B39)^5-NetDebt)/Shares -> 47.394039 | D39: =(NPV($B39,$C$27:$G$27)+($G$27*(1+D$38)/($B39-D$38))/(1+$B39)^5-NetDebt)/Shares -> 50.531953 | E39: =(NPV($B39,$C$27:$G$27)+($G$27*(1+E$38)/($B39-E$38))/(1+$B39)^5-NetDebt)/Shares -> 54.253014 | F39: =(NPV($B39,$C$27:$G$27)+($G$27*(1+F$38)/($B39-F$38))/(1+$B39)^5-NetDebt)/Shares -> 58.736431 | G39: =(NPV($B39,$C$27:$G$27)+($G$27*(1+G$38)/($B39-G$38))/(1+$B39)^5-NetDebt)/Shares -> 64.243227
B40: =WACC+-0.005 -> 0.08881 | C40: =(NPV($B40,$C$27:$G$27)+($G$27*(1+C$38)/($B40-C$38))/(1+$B40)^5-NetDebt)/Shares -> 43.984348 | D40: =(NPV($B40,$C$27:$G$27)+($G$27*(1+D$38)/($B40-D$38))/(1+$B40)^5-NetDebt)/Shares -> 46.617312 | E40: =(NPV($B40,$C$27:$G$27)+($G$27*(1+E$38)/($B40-E$38))/(1+$B40)^5-NetDebt)/Shares -> 49.697982 | F40: =(NPV($B40,$C$27:$G$27)+($G$27*(1+F$38)/($B40-F$38))/(1+$B40)^5-NetDebt)/Shares -> 53.351162 | G40: =(NPV($B40,$C$27:$G$27)+($G$27*(1+G$38)/($B40-G$38))/(1+$B40)^5-NetDebt)/Shares -> 57.752791
B41: =WACC+0 -> 0.09381 | C41: =(NPV($B41,$C$27:$G$27)+($G$27*(1+C$38)/($B41-C$38))/(1+$B41)^5-NetDebt)/Shares -> 41.037697 | D41: =(NPV($B41,$C$27:$G$27)+($G$27*(1+D$38)/($B41-D$38))/(1+$B41)^5-NetDebt)/Shares -> 43.272603 | E41: =(NPV($B41,$C$27:$G$27)+($G$27*(1+E$38)/($B41-E$38))/(1+$B41)^5-NetDebt)/Shares -> 45.857753 | F41: =(NPV($B41,$C$27:$G$27)+($G$27*(1+F$38)/($B41-F$38))/(1+$B41)^5-NetDebt)/Shares -> 48.88248 | G41: =(NPV($B41,$C$27:$G$27)+($G$27*(1+G$38)/($B41-G$38))/(1+$B41)^5-NetDebt)/Shares -> 52.469318
B42: =WACC+0.005 -> 0.09881 | C42: =(NPV($B42,$C$27:$G$27)+($G$27*(1+C$38)/($B42-C$38))/(1+$B42)^5-NetDebt)/Shares -> 38.465933 | D42: =(NPV($B42,$C$27:$G$27)+($G$27*(1+D$38)/($B42-D$38))/(1+$B42)^5-NetDebt)/Shares -> 40.381983 | E42: =(NPV($B42,$C$27:$G$27)+($G$27*(1+E$38)/($B42-E$38))/(1+$B42)^5-NetDebt)/Shares -> 42.576487 | F42: =(NPV($B42,$C$27:$G$27)+($G$27*(1+F$38)/($B42-F$38))/(1+$B42)^5-NetDebt)/Shares -> 45.114903 | G42: =(NPV($B42,$C$27:$G$27)+($G$27*(1+G$38)/($B42-G$38))/(1+$B42)^5-NetDebt)/Shares -> 48.08495
B43: =WACC+0.01 -> 0.10381 | C43: =(NPV($B43,$C$27:$G$27)+($G$27*(1+C$38)/($B43-C$38))/(1+$B43)^5-NetDebt)/Shares -> 36.201941 | D43: =(NPV($B43,$C$27:$G$27)+($G$27*(1+D$38)/($B43-D$38))/(1+$B43)^5-NetDebt)/Shares -> 37.859005 | E43: =(NPV($B43,$C$27:$G$27)+($G$27*(1+E$38)/($B43-E$38))/(1+$B43)^5-NetDebt)/Shares -> 39.740572 | F43: =(NPV($B43,$C$27:$G$27)+($G$27*(1+F$38)/($B43-F$38))/(1+$B43)^5-NetDebt)/Shares -> 41.895583 | G43: =(NPV($B43,$C$27:$G$27)+($G$27*(1+G$38)/($B43-G$38))/(1+$B43)^5-NetDebt)/Shares -> 44.388317

Sheet Scenarios
A1: SCENARIOS & SENSITIVITY
B3: Scenario | C3: Rev Growth | D3: EBITDA Margin | E3: Implied Rev ($M) | F3: Implied EBITDA | G3: Fair Value | H3: Upside
B4: Base | C4: =RevGrowthMy -> 0.16 | D4: =EbitdaMarginMy -> 0.26 | E4: =PriorRev*(1+C4) -> 1160 | F4: =E4*D4 -> 301.6 | G4: =(PeerEVEBITDA*F4-NetDebt)/Shares -> 40.708 | H4: =G4/Price-1 -> -0.095377778
B5: Bull | C5: =RevGrowthMy*1.25 -> 0.2 | D5: =EbitdaMarginMy+0.03 -> 0.29 | E5: =PriorRev*(1+C5) -> 1200 | F5: =E5*D5 -> 348 | G5: =(PeerEVEBITDA*F5-NetDebt)/Shares -> 46.74 | H5: =G5/Price-1 -> 0.038666667
B6: Bear | C6: =RevGrowthMy*0.7 -> 0.112 | D6: =EbitdaMarginMy-0.04 -> 0.22 | E6: =PriorRev*(1+C6) -> 1112 | F6: =E6*D6 -> 244.64 | G6: =(PeerEVEBITDA*F6-NetDebt)/Shares -> 33.3032 | H6: =G6/Price-1 -> -0.25992889
B8: TORNADO — Fair Value swing to ±20% driver moves
B9: Driver | C9: FV @ -20% | D9: FV @ +20% | E9: Swing
B10: Revenue Growth | C10: =(PeerEVEBITDA*(PriorRev*(1+RevGrowthMy*0.8)*EbitdaMarginMy)-NetDebt)/Shares -> 39.6264 | D10: =(PeerEVEBITDA*(PriorRev*(1+RevGrowthMy*1.2)*EbitdaMarginMy)-NetDebt)/Shares -> 41.7896 | E10: =ABS(D10-C10) -> 2.1632
B11: EBITDA Margin | C11: =(PeerEVEBITDA*(PriorRev*(1+RevGrowthMy)*EbitdaMarginMy*0.8)-NetDebt)/Shares -> 32.8664 | D11: =(PeerEVEBITDA*(PriorRev*(1+RevGrowthMy)*EbitdaMarginMy*1.2)-NetDebt)/Shares -> 48.5496 | E11: =ABS(D11-C11) -> 15.6832
B12: Peer EV/EBITDA | C12: =(PeerEVEBITDA*0.8*(PriorRev*(1+RevGrowthMy)*EbitdaMarginMy)-NetDebt)/Shares -> 32.8664 | D12: =(PeerEVEBITDA*1.2*(PriorRev*(1+RevGrowthMy)*EbitdaMarginMy)-NetDebt)/Shares -> 48.5496 | E12: =ABS(D12-C12) -> 15.6832
B13: Net Debt | C13: =(PeerEVEBITDA*(PriorRev*(1+RevGrowthMy)*EbitdaMarginMy)-NetDebt*1.2)/Shares -> 41.008 | D13: =(PeerEVEBITDA*(PriorRev*(1+RevGrowthMy)*EbitdaMarginMy)-NetDebt*0.8)/Shares -> 40.408 | E13: =ABS(D13-C13) -> 0.6
B14: Shares Out | C14: =(PeerEVEBITDA*(PriorRev*(1+RevGrowthMy)*EbitdaMarginMy)-NetDebt)/Shares*1.2 -> 48.8496 | D14: =(PeerEVEBITDA*(PriorRev*(1+RevGrowthMy)*EbitdaMarginMy)-NetDebt)/Shares*0.8 -> 32.5664 | E14: =ABS(D14-C14) -> 16.2832

Sheet Charts
A1: CHARTS
A3: Metric | B3: Consensus | C3: My Model
A4: Revenue | B4: =ConsRev -> 1150 | C4: =RevMy -> 1160
A5: EBITDA | B5: =ConsEBITDA -> 295 | C5: =EbitdaMy -> 301.6
A6: Net Income | B6: =ConsNI -> 150 | C6: =NiMy -> 156.6
A9: Active-Sector KPI | B9: Value
A10: =INDEX(KpiNames,1,MATCH(SelectedSector,SectorList,0)) -> ARR ($M) | B10: =INDEX(KpiValues,1,MATCH(SelectedSector,SectorList,0)) -> 1200
A11: =INDEX(KpiNames,2,MATCH(SelectedSector,SectorList,0)) -> Net Rev Retention (%) | B11: =INDEX(KpiValues,2,MATCH(SelectedSector,SectorList,0)) -> 118
A12: =INDEX(KpiNames,3,MATCH(SelectedSector,SectorList,0)) -> Rule of 40 (%) | B12: =INDEX(KpiValues,3,MATCH(SelectedSector,SectorList,0)) -> 46
A13: =INDEX(KpiNames,4,MATCH(SelectedSector,SectorList,0)) -> Gross Margin (%) | B13: =INDEX(KpiValues,4,MATCH(SelectedSector,SectorList,0)) -> 78
A14: =INDEX(KpiNames,5,MATCH(SelectedSector,SectorList,0)) -> CAC Payback (mo) | B14: =INDEX(KpiValues,5,MATCH(SelectedSector,SectorList,0)) -> 14
A17: Net Income Bridge | B17: Value
A18: Consensus NI | B18: =ConsNI -> 150
A19: Revenue Beat | B19: =(RevMy-ConsRev)*NiMarginMy -> 1.35
A20: Margin / Other | B20: =NiMy-ConsNI-((RevMy-ConsRev)*NiMarginMy) -> 5.25
A21: My NI | B21: =NiMy -> 156.6

Sheet SectorKPIs
A1: SECTOR KPI TEMPLATES — driven by SelectedSector
A3: KPI Names → | C3: Tech/SaaS | D3: Consumer/Retail | E3: Healthcare/Biotech | F3: Industrials | G3: Financials | H3: Energy | I3: Other
C4: ARR ($M) | D4: Same-Store Sales (%) | E4: R&D % of Rev (%) | F4: Book-to-Bill (x) | G4: Net Interest Margin (%) | H4: Production (mboe/d) | I4: Revenue Growth (%)
C5: Net Rev Retention (%) | D5: Gross Margin (%) | E5: Pipeline Assets (#) | F5: Capacity Util (%) | G5: Efficiency Ratio (%) | H5: Realized ($/boe) | I5: Gross Margin (%)
C6: Rule of 40 (%) | D6: Inventory Turns (x) | E6: Patients (k) | F6: Backlog ($M) | G6: ROE (%) | H6: Lifting Cost ($/boe) | I6: Operating Margin (%)
C7: Gross Margin (%) | D7: Store Count (#) | E7: Gross Margin (%) | F7: Operating Margin (%) | G7: Tier 1 Capital (%) | H7: Reserve Life (yr) | I7: FCF Margin (%)
C8: CAC Payback (mo) | D8: Online Mix (%) | E8: Cash Runway (mo) | F8: ROIC (%) | G8: Loan Growth (%) | H8: FCF Yield (%) | I8: ROIC (%)
A10: KPI Values → | C10: Tech/SaaS | D10: Consumer/Retail | E10: Healthcare/Biotech | F10: Industrials | G10: Financials | H10: Energy | I10: Other
C11: 1200 | D11: 4.5 | E11: 22 | F11: 1.08 | G11: 3.2 | H11: 520 | I11: 12
C12: 118 | D12: 42 | E12: 12 | F12: 84 | G12: 58 | H12: 68 | I12: 55
C13: 46 | D13: 5.2 | E13: 340 | F13: 2300 | G13: 13.5 | H13: 12.5 | I13: 20
C14: 78 | D14: 1450 | E14: 74 | F14: 16 | G14: 12.2 | H14: 9.4 | I14: 18
C15: 14 | D15: 31 | E15: 28 | F15: 13 | G15: 7 | H15: 11 | I15: 14
